accounts_api_client/__init__.py
accounts_api_client/cli.py
accounts_api_client/client.py
tests/__init__.py
tests/conftest.py
tests/test_api_client.py
tests/test_cli.py
teklia_accounts_client-0.1.6.dist-info/METADATA
teklia_accounts_client-0.1.6.dist-info/WHEEL
teklia_accounts_client-0.1.6.dist-info/entry_points.txt
teklia_accounts_client-0.1.6.dist-info/top_level.txt
teklia_accounts_client-0.1.6.dist-info/RECORD
