Metadata-Version: 2.4
Name: teklia-accounts-client
Version: 0.1.6
Summary: Official API client for Teklia account system
Author-email: Teklia <contact@teklia.com>
Maintainer-email: Teklia <contact@teklia.com>
Keywords: python
Classifier: Programming Language :: Python :: 3 :: Only
Classifier: Programming Language :: Python :: 3.10
Classifier: Programming Language :: Python :: 3.11
Classifier: Programming Language :: Python :: 3.12
Requires-Python: >=3.10
Requires-Dist: requests>=2.30
Requires-Dist: PyNaCl==1.5.0
Requires-Dist: tenacity==9.1.2
